coralinede/__init__.py
coralinede/auto_detect_df/__init__.py
coralinede/auto_detect_df/detect_datatype.py
coralinede/auto_detect_df/pyingest_util.py
coralinede-1.0.1.dist-info/LICENSE
coralinede-1.0.1.dist-info/METADATA
coralinede-1.0.1.dist-info/WHEEL
coralinede-1.0.1.dist-info/top_level.txt
coralinede-1.0.1.dist-info/RECORD
