Metadata-Version: 2.1
Name: coralinede
Version: 1.0.1
Summary: python library for data engineering
Home-page: https://github.com/coralinetech/coralinede
Author: coraline tech
Author-email: tech@coraline.co.th
License: MIT
Keywords: data-engineering,pandas,python,pandas-helper
Platform: UNKNOWN
Classifier: Development Status :: 3 - Alpha
Classifier: Intended Audience :: Developers
Classifier: Topic :: Software Development :: Build Tools
Classifier: License :: OSI Approved :: MIT License
Classifier: Programming Language :: Python :: 3
Classifier: Programming Language :: Python :: 3.4
Classifier: Programming Language :: Python :: 3.5
Classifier: Programming Language :: Python :: 3.6
Requires-Dist: sqlalchemy
Requires-Dist: pandas
Requires-Dist: numpy
